LICENSE
MANIFEST.in
README.rst
changelog
hashit.spec
setup.py
snapcraft.yaml
docs/extra.md
docs/hashes.md
docs/index.md
docs/plugins.md
docs/pydoc.md
docs/usage.md
hashit/__init__.py
hashit/__main__.py
hashit/detection.py
hashit/extra.py
hashit/version.py
hashit.egg-info/PKG-INFO
hashit.egg-info/SOURCES.txt
hashit.egg-info/dependency_links.txt
hashit.egg-info/entry_points.txt
hashit.egg-info/top_level.txt
hashit.egg-info/zip-safe
img/icon.png
tests/__init__.py
tests/config.py
tests/test_load.py
tests/unit.py