Metadata-Version: 1.1
Name: hashit
Version: 3.5.3
Summary: Hashing Application with muliple modes, settings and more! Hashit, is an hashing application used as an verification tool, intendet to replace the 'standard' linux hashing utilities such as md5sum, sha1sum and so on. One of the main reasons why this program was develop was to create an easy-to-use command line tool for newcomers and professionals alike to hash/verify files and other data. For more see our homepage at https://cjavad.github.io/hashit
Home-page: https://github.com/cjavad/hashit
Author: Javad Shafique
Author-email: javadshafique@hotmail.com
License: MIT
Platform: UNKNOWN
Classifier: Programming Language :: Python :: 2
Classifier: Programming Language :: Python :: 3
Classifier: Topic :: Security :: Cryptography
Classifier: License :: OSI Approved :: MIT License
Classifier: Environment :: Console
Classifier: Intended Audience :: Developers
Classifier: Intended Audience :: System Administrators
